LICENSE
MANIFEST.in
README.md
setup.py
django_proxy_server.egg-info/PKG-INFO
django_proxy_server.egg-info/SOURCES.txt
django_proxy_server.egg-info/dependency_links.txt
django_proxy_server.egg-info/requires.txt
django_proxy_server.egg-info/top_level.txt
proxy_server/__init__.py
proxy_server/backend_services.py
proxy_server/decorators.py
proxy_server/helpers.py
proxy_server/middleware.py
proxy_server/response.py
proxy_server/authentication/__init__.py
proxy_server/authentication/auth.py
proxy_server/authentication/middleware.py
tests/__init__.py
tests/manage.py
tests/rest_api_connection.py
tests/settings.py
tests/tests.py
tests/urls.py
tests/views.py