Metadata-Version: 1.1
Name: django-proxy-server
Version: 0.6
Summary: This is a django application to use django as a proxy server between a frontend device/server and a backend server inside a DMZ
Home-page: https://github.com/lmanzurv/django_proxy_server
Author: Laura Manzur
Author-email: lmanzurv@gmail.com
License: Apache License
Download-URL: https://github.com/lmanzurv/django_proxy_server
Keywords: django proxy service rest
Platform: UNKNOWN
Classifier: Framework :: Django
Classifier: License :: OSI Approved :: Academic Free License (AFL)
Classifier: Natural Language :: English
Classifier: Programming Language :: Python :: 2.7
